{
  "root": [
    {
      "layout": {
        "value": "12",
        "elementGroups": [
          [
            {
              "component": {
                "widgetIdentity": "group-widget-2",
                "id": "friendshipLink-1470623666551",
                "styleId": "haua-1",
                "properties": {
                  "name": "Neo",
                  "sex": "Man"
                },
                "previewHTML": "<div id=\"friendshipLink\"><h1 class=\"title\">Connect  Local.  连接一切本地生活</h1><p class=\"desc\">我是测试内容，测试内容，测试内容，测试内容，测试内容，测试内容，测试内容。</p></div>"
              }
            }
          ]
        ]
      }
    },
    {
      "layout": {
        "value": "6,6",
        "elementGroups": [
          [
            {
              "component": {
                "widgetIdentity": "group-widget-3",
                "id": "friendshipLink-1470625376083",
                "styleId": "haua-2",
                "properties": {
                  "name": "Neo",
                  "sex": "Man"
                },
                "previewHTML": "<img id=\"friendshipLink\" src=\"http://placehold.it/200x150?text=Test2-1\">"
              }
            }
          ],
          [
            {
              "component": {
                "widgetIdentity": "group-widget-4",
                "id": "friendshipLink-1470625378595",
                "styleId": null,
                "properties": {
                  "name": "Neo",
                  "sex": "Man"
                },
                "previewHTML": "<img id=\"friendshipLink\" src=\"http://placehold.it/200x150?text=Test2-1\">"
              }
            }
          ]
        ]
      }
    }
  ]
}